{
	"partitions" : [
		{
			"name" : "Top",
			"pins" : [
				{
					"name" : "saldo_novo[0]",
					"strict" : false
				},
				{
					"name" : "saldo_novo[1]",
					"strict" : false
				},
				{
					"name" : "saldo_novo[2]",
					"strict" : false
				},
				{
					"name" : "saldo_novo[3]",
					"strict" : false
				},
				{
					"name" : "saldo_novo[4]",
					"strict" : false
				},
				{
					"name" : "saldo_novo[5]",
					"strict" : false
				},
				{
					"name" : "saldo_novo[6]",
					"strict" : false
				},
				{
					"name" : "saldo_novo[7]",
					"strict" : false
				},
				{
					"name" : "saldo_novo[8]",
					"strict" : false
				},
				{
					"name" : "saldo_novo[9]",
					"strict" : false
				},
				{
					"name" : "saldo_novo[10]",
					"strict" : false
				},
				{
					"name" : "saldo_novo[11]",
					"strict" : false
				},
				{
					"name" : "saldo_novo[12]",
					"strict" : false
				},
				{
					"name" : "saldo_novo[13]",
					"strict" : false
				},
				{
					"name" : "saldo_novo[14]",
					"strict" : false
				},
				{
					"name" : "saldo_novo[15]",
					"strict" : false
				},
				{
					"name" : "status",
					"strict" : false
				},
				{
					"name" : "erro_saida",
					"strict" : false
				},
				{
					"name" : "clk",
					"strict" : false
				},
				{
					"name" : "valor_operacao[0]",
					"strict" : false
				},
				{
					"name" : "reset",
					"strict" : false
				},
				{
					"name" : "valor_operacao[5]",
					"strict" : false
				},
				{
					"name" : "valor_operacao[11]",
					"strict" : false
				},
				{
					"name" : "valor_operacao[1]",
					"strict" : false
				},
				{
					"name" : "valor_operacao[2]",
					"strict" : false
				},
				{
					"name" : "valor_operacao[3]",
					"strict" : false
				},
				{
					"name" : "valor_operacao[4]",
					"strict" : false
				},
				{
					"name" : "valor_operacao[6]",
					"strict" : false
				},
				{
					"name" : "valor_operacao[7]",
					"strict" : false
				},
				{
					"name" : "valor_operacao[8]",
					"strict" : false
				},
				{
					"name" : "valor_operacao[9]",
					"strict" : false
				},
				{
					"name" : "valor_operacao[10]",
					"strict" : false
				},
				{
					"name" : "valor_operacao[12]",
					"strict" : false
				},
				{
					"name" : "valor_operacao[13]",
					"strict" : false
				},
				{
					"name" : "valor_operacao[14]",
					"strict" : false
				},
				{
					"name" : "valor_operacao[15]",
					"strict" : false
				},
				{
					"name" : "tipo_operacao[1]",
					"strict" : false
				},
				{
					"name" : "tipo_operacao[0]",
					"strict" : false
				},
				{
					"name" : "tipo_operacao[2]",
					"strict" : false
				},
				{
					"name" : "senha_in[4]",
					"strict" : false
				},
				{
					"name" : "senha_in[5]",
					"strict" : false
				},
				{
					"name" : "senha_in[6]",
					"strict" : false
				},
				{
					"name" : "senha_in[7]",
					"strict" : false
				},
				{
					"name" : "login_in[0]",
					"strict" : false
				},
				{
					"name" : "login_in[1]",
					"strict" : false
				},
				{
					"name" : "login_in[2]",
					"strict" : false
				},
				{
					"name" : "login_in[3]",
					"strict" : false
				},
				{
					"name" : "login_in[4]",
					"strict" : false
				},
				{
					"name" : "login_in[5]",
					"strict" : false
				},
				{
					"name" : "login_in[6]",
					"strict" : false
				},
				{
					"name" : "login_in[7]",
					"strict" : false
				},
				{
					"name" : "senha_in[0]",
					"strict" : false
				},
				{
					"name" : "senha_in[1]",
					"strict" : false
				},
				{
					"name" : "senha_in[2]",
					"strict" : false
				},
				{
					"name" : "senha_in[3]",
					"strict" : false
				},
				{
					"name" : "confirma",
					"strict" : false
				},
				{
					"name" : "selecao_inicio",
					"strict" : false
				}
			]
		}
	]
}